README
destiny_bot.py
setup.py
desinty_bot.egg-info/PKG-INFO
desinty_bot.egg-info/SOURCES.txt
desinty_bot.egg-info/dependency_links.txt
desinty_bot.egg-info/entry_points.txt
desinty_bot.egg-info/top_level.txt
desinty_bot.egg-info/zip-safe