Metadata-Version: 1.0
Name: desinty-bot
Version: 0.0.1
Summary: Set of commands that scrape destinytracker.com for info.
Home-page: UNKNOWN
Author: Nolan Brubaker
Author-email: palendae@gmail.com
License: UNKNOWN
Platform: UNKNOWN
